{"stats":{"minecraft:dropped":{"minecraft:stone_hoe":1,"minecraft:dripstone_block":2,"minecraft:saddle":1,"minecraft:dirt":135,"minecraft:dandelion":1,"minecraft:stone_axe":2,"minecraft:oak_planks":5,"minecraft:oak_sapling":1,"minecraft:stone_pickaxe":1},"minecraft:custom":{"minecraft:mob_kills":2,"minecraft:animals_bred":8,"minecraft:interact_with_crafting_table":71,"minecraft:bell_ring":32,"minecraft:leave_game":5,"minecraft:time_since_death":774783,"minecraft:climb_one_cm":4118,"minecraft:sprint_one_cm":630303,"minecraft:walk_one_cm":1991865,"minecraft:drop":19,"minecraft:play_time":774783,"minecraft:sneak_time":51761,"minecraft:walk_under_water_one_cm":27306,"minecraft:jump":6068,"minecraft:interact_with_blast_furnace":4,"minecraft:walk_on_water_one_cm":65922,"minecraft:total_world_time":774783,"minecraft:interact_with_furnace":23,"minecraft:sleep_in_bed":2,"minecraft:time_since_rest":29940,"minecraft:damage_taken":2892,"minecraft:damage_dealt":231,"minecraft:swim_one_cm":19729,"minecraft:fly_one_cm":836934,"minecraft:open_chest":111,"minecraft:crouch_one_cm":97483,"minecraft:fall_one_cm":149558,"minecraft:horse_one_cm":32640},"minecraft:crafted":{"minecraft:cobbled_deepslate_slab":450,"minecraft:oak_planks":972,"minecraft:cobblestone_slab":36,"minecraft:stone_shovel":4,"minecraft:lightning_rod":1,"minecraft:furnace":1,"minecraft:cobblestone_stairs":288,"minecraft:glass":77,"minecraft:polished_diorite":128,"minecraft:melon_seeds":40,"minecraft:iron_hoe":1,"minecraft:stone_pickaxe":23,"minecraft:chest":7,"minecraft:cobbled_deepslate_stairs":204,"minecraft:jungle_fence":6,"minecraft:stone_hoe":2,"minecraft:oak_fence":147,"minecraft:crafting_table":4,"minecraft:wooden_pickaxe":2,"minecraft:copper_ingot":8,"minecraft:bucket":1,"minecraft:stone_axe":4,"minecraft:air":0,"minecraft:jungle_planks":36,"minecraft:oak_fence_gate":2,"minecraft:chiseled_deepslate":57,"minecraft:stick":208,"minecraft:iron_ingot":74,"minecraft:iron_pickaxe":2,"minecraft:iron_shovel":1,"minecraft:gold_ingot":52,"minecraft:torch":236},"minecraft:picked_up":{"minecraft:chiseled_deepslate":1,"minecraft:cocoa_beans":49,"minecraft:crafting_table":2,"minecraft:wheat":217,"minecraft:azure_bluet":3,"minecraft:cornflower":1,"minecraft:raw_copper":81,"minecraft:beetroot":2,"minecraft:smooth_stone":1,"minecraft:cobbled_deepslate":1356,"minecraft:beef":1,"minecraft:cobblestone_slab":8,"minecraft:jungle_sapling":1,"minecraft:poppy":1,"minecraft:melon_slice":94,"minecraft:egg":1,"minecraft:stick":42,"minecraft:raw_iron":74,"minecraft:oak_fence":6,"minecraft:torch":43,"minecraft:diorite":287,"minecraft:pointed_dripstone":3,"minecraft:carrot":10,"minecraft:redstone":314,"minecraft:beetroot_seeds":5,"minecraft:rail":19,"minecraft:cobblestone":1180,"minecraft:stripped_oak_log":6,"minecraft:glow_ink_sac":3,"minecraft:jungle_log":20,"minecraft:andesite":68,"minecraft:leather":2,"minecraft:flint":2,"minecraft:tuff":198,"minecraft:oak_log":335,"minecraft:cobbled_deepslate_stairs":18,"minecraft:cobblestone_stairs":3,"minecraft:lapis_lazuli":63,"minecraft:dirt":1085,"minecraft:apple":10,"minecraft:wheat_seeds":698,"minecraft:cobbled_deepslate_slab":24,"minecraft:raw_gold":64,"minecraft:bell":1,"minecraft:stone_pickaxe":1,"minecraft:oak_fence_gate":1,"minecraft:bamboo":13,"minecraft:oak_planks":26,"minecraft:pumpkin":4,"minecraft:dandelion":11,"minecraft:dripstone_block":4,"minecraft:gravel":39,"minecraft:sand":77,"minecraft:blast_furnace":1,"minecraft:white_bed":4,"minecraft:green_carpet":2,"minecraft:diamond":5,"minecraft:stone_axe":2,"minecraft:granite":125,"minecraft:melon_seeds":5,"minecraft:oak_sapling":102,"minecraft:coal":116,"minecraft:bricks":2,"minecraft:dark_oak_fence":2,"minecraft:sunflower":15},"minecraft:mined":{"minecraft:tuff":200,"minecraft:attached_melon_stem":1,"minecraft:white_bed":4,"minecraft:oak_sapling":10,"minecraft:farmland":2,"minecraft:deepslate_diamond_ore":5,"minecraft:cobbled_deepslate_stairs":21,"minecraft:cobblestone_stairs":4,"minecraft:jungle_leaves":8,"minecraft:glow_lichen":1,"minecraft:granite":125,"minecraft:dark_oak_fence":2,"minecraft:cobbled_deepslate_slab":23,"minecraft:grass_block":578,"minecraft:jungle_log":20,"minecraft:smooth_stone":1,"minecraft:carrots":6,"minecraft:iron_ore":43,"minecraft:cobbled_deepslate":8,"minecraft:andesite":68,"minecraft:chiseled_deepslate":1,"minecraft:pumpkin":4,"minecraft:deepslate_lapis_ore":10,"minecraft:azure_bluet":3,"minecraft:bell":1,"minecraft:pointed_dripstone":1,"minecraft:vine":5,"minecraft:cobblestone_slab":8,"minecraft:deepslate_iron_ore":32,"minecraft:dirt_path":1,"minecraft:rail":20,"minecraft:stripped_oak_log":6,"minecraft:green_carpet":2,"minecraft:bamboo":1,"minecraft:stone":1173,"minecraft:deepslate_redstone_ore":70,"minecraft:dandelion":9,"minecraft:cornflower":1,"minecraft:oak_fence":6,"minecraft:crafting_table":2,"minecraft:torch":15,"minecraft:blast_furnace":1,"minecraft:melon":17,"minecraft:glass":8,"minecraft:tall_grass":48,"minecraft:copper_ore":24,"minecraft:cobblestone":29,"minecraft:lapis_ore":1,"minecraft:deepslate_gold_ore":63,"minecraft:sugar_cane":1,"minecraft:oak_planks":30,"minecraft:bricks":2,"minecraft:diorite":287,"minecraft:wall_torch":25,"minecraft:deepslate_copper_ore":1,"minecraft:wheat":268,"minecraft:grass":348,"minecraft:oak_log":341,"minecraft:coal_ore":119,"minecraft:beetroots":2,"minecraft:cocoa":17,"minecraft:oak_fence_gate":1,"minecraft:dripstone_block":2,"minecraft:sunflower":18,"minecraft:gravel":43,"minecraft:sand":78,"minecraft:dirt":543,"minecraft:gold_ore":1,"minecraft:oak_leaves":127,"minecraft:deepslate":1365,"minecraft:fern":1},"minecraft:used":{"minecraft:oak_fence":151,"minecraft:iron_shovel":254,"minecraft:chiseled_deepslate":1,"minecraft:stone_shovel":529,"minecraft:chest":7,"minecraft:bell":1,"minecraft:stone_hoe":286,"minecraft:torch":292,"minecraft:dirt":321,"minecraft:cocoa_beans":6,"minecraft:carrot":12,"minecraft:tuff":37,"minecraft:oak_fence_gate":3,"minecraft:polished_diorite":112,"minecraft:iron_hoe":268,"minecraft:jungle_sapling":1,"minecraft:glass":69,"minecraft:melon_seeds":36,"minecraft:bamboo":3,"minecraft:oak_sapling":92,"minecraft:furnace":1,"minecraft:beetroot_seeds":7,"minecraft:egg":1,"minecraft:cobbled_deepslate":379,"minecraft:wheat_seeds":683,"minecraft:water_bucket":16,"minecraft:diorite":2,"minecraft:cobblestone_stairs":260,"minecraft:stone_pickaxe":2894,"minecraft:oak_planks":601,"minecraft:wooden_pickaxe":120,"minecraft:cobblestone_slab":43,"minecraft:crafting_table":6,"minecraft:blast_furnace":1,"minecraft:white_bed":3,"minecraft:dripstone_block":1,"minecraft:cobbled_deepslate_stairs":188,"minecraft:pumpkin_seeds":4,"minecraft:lightning_rod":1,"minecraft:oak_log":28,"minecraft:sunflower":15,"minecraft:iron_pickaxe":755,"minecraft:stone_axe":491,"minecraft:cobbled_deepslate_slab":351,"minecraft:cobblestone":358,"minecraft:bucket":16,"minecraft:stripped_oak_log":1,"minecraft:dandelion":5},"minecraft:broken":{"minecraft:iron_shovel":1,"minecraft:stone_hoe":1,"minecraft:wooden_pickaxe":2,"minecraft:stone_pickaxe":22,"minecraft:stone_axe":3,"minecraft:iron_pickaxe":3,"minecraft:stone_shovel":3,"minecraft:iron_hoe":1},"minecraft:killed":{"minecraft:glow_squid":1,"minecraft:cow":1}},"DataVersion":2975}